[
  {
    "Name":"Alex Rodriguez",
    "Team":"SEA",
    "G":148,
    "PA":672,
    "HR":41,
    "RBI":132,
    "AVG":0.316,
    "WAR":9.5,
    "year":2000
  },
  {
    "Name":"Darin Erstad",
    "Team":"ANA",
    "G":157,
    "PA":747,
    "HR":25,
    "RBI":100,
    "AVG":0.355,
    "WAR":8.7,
    "year":2000
  },
  {
    "Name":"Todd Helton",
    "Team":"COL",
    "G":160,
    "PA":697,
    "HR":42,
    "RBI":147,
    "AVG":0.372,
    "WAR":8.3,
    "year":2000
  },
  {
    "Name":"Troy Glaus",
    "Team":"ANA",
    "G":159,
    "PA":678,
    "HR":47,
    "RBI":102,
    "AVG":0.284,
    "WAR":8.2,
    "year":2000
  },
  {
    "Name":"Jason Giambi",
    "Team":"OAK",
    "G":152,
    "PA":664,
    "HR":43,
    "RBI":137,
    "AVG":0.333,
    "WAR":7.7,
    "year":2000
  },
  {
    "Name":"Andruw Jones",
    "Team":"ATL",
    "G":161,
    "PA":729,
    "HR":36,
    "RBI":104,
    "AVG":0.303,
    "WAR":7.7,
    "year":2000
  },
  {
    "Name":"Barry Bonds",
    "Team":"SFG",
    "G":143,
    "PA":607,
    "HR":49,
    "RBI":106,
    "AVG":0.306,
    "WAR":7.6,
    "year":2000
  },
  {
    "Name":"Nomar Garciaparra",
    "Team":"BOS",
    "G":140,
    "PA":599,
    "HR":21,
    "RBI":96,
    "AVG":0.372,
    "WAR":7.6,
    "year":2000
  },
  {
    "Name":"Carlos Delgado",
    "Team":"TOR",
    "G":162,
    "PA":711,
    "HR":41,
    "RBI":137,
    "AVG":0.344,
    "WAR":7.4,
    "year":2000
  },
  {
    "Name":"Jeff Kent",
    "Team":"SFG",
    "G":159,
    "PA":695,
    "HR":33,
    "RBI":125,
    "AVG":0.334,
    "WAR":7.4,
    "year":2000
  },
  {
    "Name":"Richard Hidalgo",
    "Team":"HOU",
    "G":153,
    "PA":644,
    "HR":44,
    "RBI":122,
    "AVG":0.314,
    "WAR":7.3,
    "year":2000
  },
  {
    "Name":"Bobby Abreu",
    "Team":"PHI",
    "G":154,
    "PA":680,
    "HR":25,
    "RBI":79,
    "AVG":0.316,
    "WAR":6.9,
    "year":2000
  },
  {
    "Name":"Gary Sheffield",
    "Team":"LAD",
    "G":141,
    "PA":612,
    "HR":43,
    "RBI":109,
    "AVG":0.325,
    "WAR":6.6,
    "year":2000
  },
  {
    "Name":"Jim Edmonds",
    "Team":"STL",
    "G":152,
    "PA":643,
    "HR":42,
    "RBI":108,
    "AVG":0.295,
    "WAR":6.5,
    "year":2000
  },
  {
    "Name":"Edgardo Alfonzo",
    "Team":"NYM",
    "G":150,
    "PA":650,
    "HR":25,
    "RBI":94,
    "AVG":0.324,
    "WAR":6.4,
    "year":2000
  },
  {
    "Name":"Brian Giles",
    "Team":"PIT",
    "G":156,
    "PA":688,
    "HR":35,
    "RBI":123,
    "AVG":0.315,
    "WAR":6.3,
    "year":2000
  },
  {
    "Name":"Vladimir Guerrero",
    "Team":"MON",
    "G":154,
    "PA":641,
    "HR":44,
    "RBI":123,
    "AVG":0.345,
    "WAR":6.2,
    "year":2000
  },
  {
    "Name":"Jorge Posada",
    "Team":"NYY",
    "G":151,
    "PA":624,
    "HR":28,
    "RBI":86,
    "AVG":0.287,
    "WAR":6.1,
    "year":2000
  },
  {
    "Name":"Chipper Jones",
    "Team":"ATL",
    "G":156,
    "PA":686,
    "HR":36,
    "RBI":111,
    "AVG":0.311,
    "WAR":6.0,
    "year":2000
  },
  {
    "Name":"Frank Thomas",
    "Team":"CHW",
    "G":159,
    "PA":707,
    "HR":43,
    "RBI":143,
    "AVG":0.328,
    "WAR":5.9,
    "year":2000
  },
  {
    "Name":"Jeff Bagwell",
    "Team":"HOU",
    "G":159,
    "PA":719,
    "HR":47,
    "RBI":132,
    "AVG":0.31,
    "WAR":5.9,
    "year":2000
  },
  {
    "Name":"Sammy Sosa",
    "Team":"CHC",
    "G":156,
    "PA":705,
    "HR":50,
    "RBI":138,
    "AVG":0.32,
    "WAR":5.8,
    "year":2000
  },
  {
    "Name":"Mike Piazza",
    "Team":"NYM",
    "G":136,
    "PA":545,
    "HR":38,
    "RBI":113,
    "AVG":0.324,
    "WAR":5.8,
    "year":2000
  },
  {
    "Name":"Ken Griffey Jr.",
    "Team":"CIN",
    "G":145,
    "PA":631,
    "HR":40,
    "RBI":118,
    "AVG":0.271,
    "WAR":5.4,
    "year":2000
  },
  {
    "Name":"Edgar Martinez",
    "Team":"SEA",
    "G":153,
    "PA":665,
    "HR":37,
    "RBI":145,
    "AVG":0.324,
    "WAR":5.3,
    "year":2000
  },
  {
    "Name":"Charles Johnson",
    "Team":"- - -",
    "G":128,
    "PA":478,
    "HR":31,
    "RBI":91,
    "AVG":0.304,
    "WAR":5.3,
    "year":2000
  },
  {
    "Name":"David Justice",
    "Team":"- - -",
    "G":146,
    "PA":606,
    "HR":41,
    "RBI":118,
    "AVG":0.286,
    "WAR":5.2,
    "year":2000
  },
  {
    "Name":"Roberto Alomar",
    "Team":"CLE",
    "G":155,
    "PA":697,
    "HR":19,
    "RBI":89,
    "AVG":0.31,
    "WAR":5.0,
    "year":2000
  },
  {
    "Name":"Bernie Williams",
    "Team":"NYY",
    "G":141,
    "PA":616,
    "HR":30,
    "RBI":121,
    "AVG":0.307,
    "WAR":4.9,
    "year":2000
  },
  {
    "Name":"Shannon Stewart",
    "Team":"TOR",
    "G":136,
    "PA":631,
    "HR":21,
    "RBI":69,
    "AVG":0.319,
    "WAR":4.9,
    "year":2000
  },
  {
    "Name":"Manny Ramirez",
    "Team":"CLE",
    "G":118,
    "PA":532,
    "HR":38,
    "RBI":122,
    "AVG":0.351,
    "WAR":4.8,
    "year":2000
  },
  {
    "Name":"Jason Kendall",
    "Team":"PIT",
    "G":152,
    "PA":678,
    "HR":14,
    "RBI":58,
    "AVG":0.32,
    "WAR":4.8,
    "year":2000
  },
  {
    "Name":"Ivan Rodriguez",
    "Team":"TEX",
    "G":91,
    "PA":389,
    "HR":27,
    "RBI":83,
    "AVG":0.347,
    "WAR":4.7,
    "year":2000
  },
  {
    "Name":"Carl Everett",
    "Team":"BOS",
    "G":137,
    "PA":561,
    "HR":34,
    "RBI":108,
    "AVG":0.3,
    "WAR":4.7,
    "year":2000
  },
  {
    "Name":"Luis Gonzalez",
    "Team":"ARI",
    "G":162,
    "PA":722,
    "HR":31,
    "RBI":114,
    "AVG":0.311,
    "WAR":4.7,
    "year":2000
  },
  {
    "Name":"Mark McGwire",
    "Team":"STL",
    "G":89,
    "PA":321,
    "HR":32,
    "RBI":73,
    "AVG":0.305,
    "WAR":4.6,
    "year":2000
  },
  {
    "Name":"Scott Rolen",
    "Team":"PHI",
    "G":128,
    "PA":541,
    "HR":26,
    "RBI":89,
    "AVG":0.298,
    "WAR":4.6,
    "year":2000
  },
  {
    "Name":"Phil Nevin",
    "Team":"SDP",
    "G":143,
    "PA":605,
    "HR":31,
    "RBI":107,
    "AVG":0.303,
    "WAR":4.6,
    "year":2000
  },
  {
    "Name":"Travis Fryman",
    "Team":"CLE",
    "G":155,
    "PA":658,
    "HR":22,
    "RBI":106,
    "AVG":0.321,
    "WAR":4.6,
    "year":2000
  },
  {
    "Name":"Geoff Jenkins",
    "Team":"MIL",
    "G":135,
    "PA":564,
    "HR":34,
    "RBI":94,
    "AVG":0.303,
    "WAR":4.5,
    "year":2000
  },
  {
    "Name":"Tim Salmon",
    "Team":"ANA",
    "G":158,
    "PA":680,
    "HR":34,
    "RBI":97,
    "AVG":0.29,
    "WAR":4.5,
    "year":2000
  },
  {
    "Name":"Johnny Damon",
    "Team":"KCR",
    "G":159,
    "PA":741,
    "HR":16,
    "RBI":88,
    "AVG":0.327,
    "WAR":4.5,
    "year":2000
  },
  {
    "Name":"Jose Valentin",
    "Team":"CHW",
    "G":144,
    "PA":648,
    "HR":25,
    "RBI":92,
    "AVG":0.273,
    "WAR":4.5,
    "year":2000
  },
  {
    "Name":"Ellis Burks",
    "Team":"SFG",
    "G":122,
    "PA":458,
    "HR":24,
    "RBI":96,
    "AVG":0.344,
    "WAR":4.4,
    "year":2000
  },
  {
    "Name":"Jim Thome",
    "Team":"CLE",
    "G":158,
    "PA":684,
    "HR":37,
    "RBI":106,
    "AVG":0.269,
    "WAR":4.4,
    "year":2000
  },
  {
    "Name":"Jose Vidro",
    "Team":"MON",
    "G":153,
    "PA":663,
    "HR":24,
    "RBI":97,
    "AVG":0.33,
    "WAR":4.3,
    "year":2000
  },
  {
    "Name":"Bobby Higginson",
    "Team":"DET",
    "G":154,
    "PA":679,
    "HR":30,
    "RBI":102,
    "AVG":0.3,
    "WAR":4.3,
    "year":2000
  },
  {
    "Name":"Jermaine Dye",
    "Team":"KCR",
    "G":157,
    "PA":679,
    "HR":33,
    "RBI":118,
    "AVG":0.321,
    "WAR":4.2,
    "year":2000
  },
  {
    "Name":"Damion Easley",
    "Team":"DET",
    "G":126,
    "PA":535,
    "HR":14,
    "RBI":58,
    "AVG":0.259,
    "WAR":4.0,
    "year":2000
  },
  {
    "Name":"Adrian Beltre",
    "Team":"LAD",
    "G":138,
    "PA":575,
    "HR":20,
    "RBI":85,
    "AVG":0.29,
    "WAR":3.9,
    "year":2000
  },
  {
    "Name":"Brad Ausmus",
    "Team":"DET",
    "G":150,
    "PA":604,
    "HR":7,
    "RBI":51,
    "AVG":0.266,
    "WAR":3.9,
    "year":2000
  },
  {
    "Name":"Will Clark",
    "Team":"- - -",
    "G":130,
    "PA":507,
    "HR":21,
    "RBI":70,
    "AVG":0.319,
    "WAR":3.8,
    "year":2000
  },
  {
    "Name":"J.D. Drew",
    "Team":"STL",
    "G":135,
    "PA":486,
    "HR":18,
    "RBI":57,
    "AVG":0.295,
    "WAR":3.8,
    "year":2000
  },
  {
    "Name":"Luis Castillo",
    "Team":"FLA",
    "G":136,
    "PA":626,
    "HR":2,
    "RBI":17,
    "AVG":0.334,
    "WAR":3.8,
    "year":2000
  },
  {
    "Name":"Sean Casey",
    "Team":"CIN",
    "G":133,
    "PA":545,
    "HR":20,
    "RBI":85,
    "AVG":0.315,
    "WAR":3.7,
    "year":2000
  },
  {
    "Name":"Derek Jeter",
    "Team":"NYY",
    "G":148,
    "PA":679,
    "HR":15,
    "RBI":73,
    "AVG":0.339,
    "WAR":3.7,
    "year":2000
  },
  {
    "Name":"John Olerud",
    "Team":"SEA",
    "G":159,
    "PA":683,
    "HR":14,
    "RBI":103,
    "AVG":0.285,
    "WAR":3.6,
    "year":2000
  },
  {
    "Name":"Mike Cameron",
    "Team":"SEA",
    "G":155,
    "PA":643,
    "HR":19,
    "RBI":78,
    "AVG":0.267,
    "WAR":3.6,
    "year":2000
  },
  {
    "Name":"Eric Young",
    "Team":"CHC",
    "G":153,
    "PA":690,
    "HR":6,
    "RBI":47,
    "AVG":0.297,
    "WAR":3.6,
    "year":2000
  },
  {
    "Name":"Miguel Tejada",
    "Team":"OAK",
    "G":160,
    "PA":681,
    "HR":30,
    "RBI":115,
    "AVG":0.275,
    "WAR":3.5,
    "year":2000
  },
  {
    "Name":"Mike Sweeney",
    "Team":"KCR",
    "G":159,
    "PA":717,
    "HR":29,
    "RBI":144,
    "AVG":0.333,
    "WAR":3.3,
    "year":2000
  },
  {
    "Name":"Steve Finley",
    "Team":"ARI",
    "G":152,
    "PA":623,
    "HR":35,
    "RBI":96,
    "AVG":0.28,
    "WAR":3.3,
    "year":2000
  },
  {
    "Name":"Rafael Furcal",
    "Team":"ATL",
    "G":131,
    "PA":542,
    "HR":4,
    "RBI":37,
    "AVG":0.295,
    "WAR":3.3,
    "year":2000
  },
  {
    "Name":"Moises Alou",
    "Team":"HOU",
    "G":126,
    "PA":517,
    "HR":30,
    "RBI":114,
    "AVG":0.355,
    "WAR":3.2,
    "year":2000
  },
  {
    "Name":"John Vander Wal",
    "Team":"PIT",
    "G":134,
    "PA":461,
    "HR":24,
    "RBI":94,
    "AVG":0.299,
    "WAR":3.2,
    "year":2000
  },
  {
    "Name":"Ryan Klesko",
    "Team":"SDP",
    "G":145,
    "PA":590,
    "HR":26,
    "RBI":92,
    "AVG":0.283,
    "WAR":3.2,
    "year":2000
  },
  {
    "Name":"Shawn Green",
    "Team":"LAD",
    "G":162,
    "PA":714,
    "HR":24,
    "RBI":99,
    "AVG":0.269,
    "WAR":3.2,
    "year":2000
  },
  {
    "Name":"Rafael Palmeiro",
    "Team":"TEX",
    "G":158,
    "PA":678,
    "HR":39,
    "RBI":120,
    "AVG":0.288,
    "WAR":3.1,
    "year":2000
  },
  {
    "Name":"Fernando Vina",
    "Team":"STL",
    "G":123,
    "PA":554,
    "HR":4,
    "RBI":31,
    "AVG":0.3,
    "WAR":3.1,
    "year":2000
  },
  {
    "Name":"Jeff Cirillo",
    "Team":"COL",
    "G":157,
    "PA":684,
    "HR":11,
    "RBI":115,
    "AVG":0.326,
    "WAR":3.0,
    "year":2000
  },
  {
    "Name":"Mark Grace",
    "Team":"CHC",
    "G":143,
    "PA":621,
    "HR":11,
    "RBI":82,
    "AVG":0.28,
    "WAR":3.0,
    "year":2000
  },
  {
    "Name":"Kenny Lofton",
    "Team":"CLE",
    "G":137,
    "PA":640,
    "HR":15,
    "RBI":73,
    "AVG":0.278,
    "WAR":3.0,
    "year":2000
  },
  {
    "Name":"Mike Lieberthal",
    "Team":"PHI",
    "G":108,
    "PA":438,
    "HR":15,
    "RBI":71,
    "AVG":0.278,
    "WAR":2.9,
    "year":2000
  },
  {
    "Name":"Darrin Fletcher",
    "Team":"TOR",
    "G":122,
    "PA":445,
    "HR":20,
    "RBI":58,
    "AVG":0.32,
    "WAR":2.8,
    "year":2000
  },
  {
    "Name":"Javy Lopez",
    "Team":"ATL",
    "G":134,
    "PA":525,
    "HR":24,
    "RBI":89,
    "AVG":0.287,
    "WAR":2.8,
    "year":2000
  },
  {
    "Name":"Tony Batista",
    "Team":"TOR",
    "G":154,
    "PA":664,
    "HR":41,
    "RBI":114,
    "AVG":0.263,
    "WAR":2.7,
    "year":2000
  },
  {
    "Name":"Quilvio Veras",
    "Team":"ATL",
    "G":84,
    "PA":364,
    "HR":5,
    "RBI":37,
    "AVG":0.309,
    "WAR":2.7,
    "year":2000
  },
  {
    "Name":"Todd Zeile",
    "Team":"NYM",
    "G":153,
    "PA":623,
    "HR":22,
    "RBI":79,
    "AVG":0.268,
    "WAR":2.7,
    "year":2000
  },
  {
    "Name":"Ray Durham",
    "Team":"CHW",
    "G":151,
    "PA":709,
    "HR":17,
    "RBI":75,
    "AVG":0.28,
    "WAR":2.7,
    "year":2000
  },
  {
    "Name":"Todd Hundley",
    "Team":"LAD",
    "G":90,
    "PA":353,
    "HR":24,
    "RBI":70,
    "AVG":0.284,
    "WAR":2.6,
    "year":2000
  },
  {
    "Name":"Corey Koskie",
    "Team":"MIN",
    "G":146,
    "PA":559,
    "HR":9,
    "RBI":65,
    "AVG":0.3,
    "WAR":2.6,
    "year":2000
  },
  {
    "Name":"Trot Nixon",
    "Team":"BOS",
    "G":123,
    "PA":502,
    "HR":12,
    "RBI":60,
    "AVG":0.276,
    "WAR":2.6,
    "year":2000
  },
  {
    "Name":"Chad Kreuter",
    "Team":"LAD",
    "G":80,
    "PA":271,
    "HR":6,
    "RBI":28,
    "AVG":0.264,
    "WAR":2.6,
    "year":2000
  },
  {
    "Name":"Herbert Perry",
    "Team":"- - -",
    "G":116,
    "PA":450,
    "HR":12,
    "RBI":62,
    "AVG":0.302,
    "WAR":2.6,
    "year":2000
  },
  {
    "Name":"Mike Lowell",
    "Team":"FLA",
    "G":140,
    "PA":583,
    "HR":22,
    "RBI":91,
    "AVG":0.27,
    "WAR":2.6,
    "year":2000
  },
  {
    "Name":"Damian Jackson",
    "Team":"SDP",
    "G":138,
    "PA":541,
    "HR":6,
    "RBI":37,
    "AVG":0.255,
    "WAR":2.6,
    "year":2000
  },
  {
    "Name":"Chris Stynes",
    "Team":"CIN",
    "G":119,
    "PA":420,
    "HR":12,
    "RBI":40,
    "AVG":0.334,
    "WAR":2.5,
    "year":2000
  },
  {
    "Name":"Barry Larkin",
    "Team":"CIN",
    "G":102,
    "PA":447,
    "HR":11,
    "RBI":41,
    "AVG":0.313,
    "WAR":2.5,
    "year":2000
  },
  {
    "Name":"Rondell White",
    "Team":"- - -",
    "G":94,
    "PA":396,
    "HR":13,
    "RBI":61,
    "AVG":0.311,
    "WAR":2.5,
    "year":2000
  },
  {
    "Name":"Raul Mondesi",
    "Team":"TOR",
    "G":96,
    "PA":426,
    "HR":24,
    "RBI":67,
    "AVG":0.271,
    "WAR":2.5,
    "year":2000
  },
  {
    "Name":"Delino DeShields",
    "Team":"BAL",
    "G":151,
    "PA":643,
    "HR":10,
    "RBI":86,
    "AVG":0.296,
    "WAR":2.5,
    "year":2000
  },
  {
    "Name":"Mark Kotsay",
    "Team":"FLA",
    "G":152,
    "PA":578,
    "HR":12,
    "RBI":57,
    "AVG":0.298,
    "WAR":2.5,
    "year":2000
  },
  {
    "Name":"Rich Aurilia",
    "Team":"SFG",
    "G":141,
    "PA":571,
    "HR":20,
    "RBI":79,
    "AVG":0.271,
    "WAR":2.5,
    "year":2000
  },
  {
    "Name":"Omar Vizquel",
    "Team":"CLE",
    "G":156,
    "PA":717,
    "HR":7,
    "RBI":66,
    "AVG":0.287,
    "WAR":2.5,
    "year":2000
  },
  {
    "Name":"Alex Ochoa",
    "Team":"CIN",
    "G":118,
    "PA":275,
    "HR":13,
    "RBI":58,
    "AVG":0.316,
    "WAR":2.4,
    "year":2000
  },
  {
    "Name":"Lance Berkman",
    "Team":"HOU",
    "G":114,
    "PA":417,
    "HR":21,
    "RBI":67,
    "AVG":0.297,
    "WAR":2.4,
    "year":2000
  },
  {
    "Name":"Greg Colbrunn",
    "Team":"ARI",
    "G":116,
    "PA":385,
    "HR":15,
    "RBI":57,
    "AVG":0.313,
    "WAR":2.4,
    "year":2000
  },
  {
    "Name":"Cliff Floyd",
    "Team":"FLA",
    "G":121,
    "PA":487,
    "HR":22,
    "RBI":91,
    "AVG":0.3,
    "WAR":2.4,
    "year":2000
  },
  {
    "Name":"B.J. Surhoff",
    "Team":"- - -",
    "G":147,
    "PA":587,
    "HR":14,
    "RBI":68,
    "AVG":0.291,
    "WAR":2.4,
    "year":2000
  },
  {
    "Name":"Deivi Cruz",
    "Team":"DET",
    "G":156,
    "PA":615,
    "HR":10,
    "RBI":82,
    "AVG":0.302,
    "WAR":2.4,
    "year":2000
  },
  {
    "Name":"Magglio Ordonez",
    "Team":"CHW",
    "G":153,
    "PA":665,
    "HR":32,
    "RBI":126,
    "AVG":0.315,
    "WAR":2.3,
    "year":2000
  },
  {
    "Name":"Mitch Meluskey",
    "Team":"HOU",
    "G":117,
    "PA":400,
    "HR":14,
    "RBI":69,
    "AVG":0.3,
    "WAR":2.3,
    "year":2000
  },
  {
    "Name":"Matt Lawton",
    "Team":"MIN",
    "G":156,
    "PA":664,
    "HR":13,
    "RBI":88,
    "AVG":0.305,
    "WAR":2.3,
    "year":2000
  },
  {
    "Name":"Jose Cruz",
    "Team":"TOR",
    "G":162,
    "PA":681,
    "HR":31,
    "RBI":76,
    "AVG":0.242,
    "WAR":2.3,
    "year":2000
  },
  {
    "Name":"Damian Miller",
    "Team":"ARI",
    "G":100,
    "PA":364,
    "HR":10,
    "RBI":44,
    "AVG":0.275,
    "WAR":2.3,
    "year":2000
  },
  {
    "Name":"Marvin Benard",
    "Team":"SFG",
    "G":149,
    "PA":633,
    "HR":12,
    "RBI":55,
    "AVG":0.263,
    "WAR":2.3,
    "year":2000
  },
  {
    "Name":"Mike Matheny",
    "Team":"STL",
    "G":128,
    "PA":464,
    "HR":6,
    "RBI":47,
    "AVG":0.261,
    "WAR":2.3,
    "year":2000
  },
  {
    "Name":"David Segui",
    "Team":"- - -",
    "G":150,
    "PA":634,
    "HR":19,
    "RBI":103,
    "AVG":0.334,
    "WAR":2.2,
    "year":2000
  },
  {
    "Name":"Michael Tucker",
    "Team":"CIN",
    "G":148,
    "PA":323,
    "HR":15,
    "RBI":36,
    "AVG":0.267,
    "WAR":2.2,
    "year":2000
  },
  {
    "Name":"Greg Vaughn",
    "Team":"TBD",
    "G":127,
    "PA":545,
    "HR":28,
    "RBI":74,
    "AVG":0.254,
    "WAR":2.2,
    "year":2000
  },
  {
    "Name":"Ben Grieve",
    "Team":"OAK",
    "G":158,
    "PA":675,
    "HR":27,
    "RBI":104,
    "AVG":0.279,
    "WAR":2.2,
    "year":2000
  },
  {
    "Name":"Ron Gant",
    "Team":"- - -",
    "G":123,
    "PA":487,
    "HR":26,
    "RBI":54,
    "AVG":0.249,
    "WAR":2.2,
    "year":2000
  },
  {
    "Name":"Garret Anderson",
    "Team":"ANA",
    "G":159,
    "PA":681,
    "HR":35,
    "RBI":117,
    "AVG":0.286,
    "WAR":2.2,
    "year":2000
  },
  {
    "Name":"Bengie Molina",
    "Team":"ANA",
    "G":130,
    "PA":513,
    "HR":14,
    "RBI":71,
    "AVG":0.281,
    "WAR":2.2,
    "year":2000
  },
  {
    "Name":"Benny Agbayani",
    "Team":"NYM",
    "G":119,
    "PA":415,
    "HR":15,
    "RBI":60,
    "AVG":0.289,
    "WAR":2.1,
    "year":2000
  },
  {
    "Name":"Carlos Lee",
    "Team":"CHW",
    "G":152,
    "PA":619,
    "HR":24,
    "RBI":92,
    "AVG":0.301,
    "WAR":2.1,
    "year":2000
  },
  {
    "Name":"Joe Randa",
    "Team":"KCR",
    "G":158,
    "PA":665,
    "HR":15,
    "RBI":106,
    "AVG":0.304,
    "WAR":2.1,
    "year":2000
  },
  {
    "Name":"Randy Velarde",
    "Team":"OAK",
    "G":122,
    "PA":546,
    "HR":12,
    "RBI":41,
    "AVG":0.278,
    "WAR":2.1,
    "year":2000
  },
  {
    "Name":"Pokey Reese",
    "Team":"CIN",
    "G":135,
    "PA":577,
    "HR":12,
    "RBI":46,
    "AVG":0.255,
    "WAR":2.1,
    "year":2000
  },
  {
    "Name":"Eric Chavez",
    "Team":"OAK",
    "G":153,
    "PA":569,
    "HR":26,
    "RBI":86,
    "AVG":0.277,
    "WAR":2.0,
    "year":2000
  },
  {
    "Name":"Bobby Estalella",
    "Team":"SFG",
    "G":106,
    "PA":361,
    "HR":14,
    "RBI":53,
    "AVG":0.234,
    "WAR":2.0,
    "year":2000
  },
  {
    "Name":"Mike Bordick",
    "Team":"- - -",
    "G":156,
    "PA":644,
    "HR":20,
    "RBI":80,
    "AVG":0.285,
    "WAR":2.0,
    "year":2000
  },
  {
    "Name":"Jay Payton",
    "Team":"NYM",
    "G":149,
    "PA":529,
    "HR":17,
    "RBI":62,
    "AVG":0.291,
    "WAR":2.0,
    "year":2000
  },
  {
    "Name":"Edgar Renteria",
    "Team":"STL",
    "G":150,
    "PA":643,
    "HR":16,
    "RBI":76,
    "AVG":0.278,
    "WAR":2.0,
    "year":2000
  },
  {
    "Name":"Placido Polanco",
    "Team":"STL",
    "G":118,
    "PA":350,
    "HR":5,
    "RBI":39,
    "AVG":0.316,
    "WAR":2.0,
    "year":2000
  },
  {
    "Name":"Larry Walker",
    "Team":"COL",
    "G":87,
    "PA":372,
    "HR":9,
    "RBI":51,
    "AVG":0.309,
    "WAR":1.9,
    "year":2000
  },
  {
    "Name":"Mo Vaughn",
    "Team":"ANA",
    "G":161,
    "PA":712,
    "HR":36,
    "RBI":117,
    "AVG":0.272,
    "WAR":1.9,
    "year":2000
  },
  {
    "Name":"Kevin Millar",
    "Team":"FLA",
    "G":123,
    "PA":305,
    "HR":14,
    "RBI":42,
    "AVG":0.259,
    "WAR":1.9,
    "year":2000
  },
  {
    "Name":"Brook Fordyce",
    "Team":"- - -",
    "G":93,
    "PA":330,
    "HR":14,
    "RBI":49,
    "AVG":0.301,
    "WAR":1.9,
    "year":2000
  },
  {
    "Name":"Aaron Boone",
    "Team":"CIN",
    "G":84,
    "PA":332,
    "HR":12,
    "RBI":43,
    "AVG":0.285,
    "WAR":1.9,
    "year":2000
  },
  {
    "Name":"Preston Wilson",
    "Team":"FLA",
    "G":161,
    "PA":674,
    "HR":31,
    "RBI":121,
    "AVG":0.264,
    "WAR":1.9,
    "year":2000
  },
  {
    "Name":"Robin Ventura",
    "Team":"NYM",
    "G":141,
    "PA":551,
    "HR":24,
    "RBI":84,
    "AVG":0.232,
    "WAR":1.9,
    "year":2000
  },
  {
    "Name":"Ken Caminiti",
    "Team":"HOU",
    "G":59,
    "PA":253,
    "HR":15,
    "RBI":45,
    "AVG":0.303,
    "WAR":1.8,
    "year":2000
  },
  {
    "Name":"Derrek Lee",
    "Team":"FLA",
    "G":158,
    "PA":546,
    "HR":28,
    "RBI":70,
    "AVG":0.281,
    "WAR":1.8,
    "year":2000
  },
  {
    "Name":"Fernando Tatis",
    "Team":"STL",
    "G":96,
    "PA":394,
    "HR":18,
    "RBI":64,
    "AVG":0.253,
    "WAR":1.8,
    "year":2000
  },
  {
    "Name":"Terrence Long",
    "Team":"OAK",
    "G":138,
    "PA":631,
    "HR":18,
    "RBI":80,
    "AVG":0.288,
    "WAR":1.8,
    "year":2000
  },
  {
    "Name":"Todd Hollandsworth",
    "Team":"- - -",
    "G":137,
    "PA":471,
    "HR":19,
    "RBI":47,
    "AVG":0.269,
    "WAR":1.8,
    "year":2000
  },
  {
    "Name":"Ronnie Belliard",
    "Team":"MIL",
    "G":152,
    "PA":667,
    "HR":8,
    "RBI":54,
    "AVG":0.263,
    "WAR":1.8,
    "year":2000
  },
  {
    "Name":"Brian Jordan",
    "Team":"ATL",
    "G":133,
    "PA":537,
    "HR":17,
    "RBI":77,
    "AVG":0.264,
    "WAR":1.8,
    "year":2000
  },
  {
    "Name":"Jeffrey Hammonds",
    "Team":"COL",
    "G":122,
    "PA":511,
    "HR":20,
    "RBI":106,
    "AVG":0.335,
    "WAR":1.7,
    "year":2000
  },
  {
    "Name":"Juan Gonzalez",
    "Team":"DET",
    "G":115,
    "PA":496,
    "HR":22,
    "RBI":67,
    "AVG":0.289,
    "WAR":1.7,
    "year":2000
  },
  {
    "Name":"Dmitri Young",
    "Team":"CIN",
    "G":152,
    "PA":593,
    "HR":18,
    "RBI":88,
    "AVG":0.303,
    "WAR":1.7,
    "year":2000
  },
  {
    "Name":"Jeromy Burnitz",
    "Team":"MIL",
    "G":161,
    "PA":686,
    "HR":31,
    "RBI":98,
    "AVG":0.232,
    "WAR":1.7,
    "year":2000
  },
  {
    "Name":"Brady Anderson",
    "Team":"BAL",
    "G":141,
    "PA":618,
    "HR":19,
    "RBI":50,
    "AVG":0.257,
    "WAR":1.7,
    "year":2000
  },
  {
    "Name":"Orlando Palmeiro",
    "Team":"ANA",
    "G":108,
    "PA":296,
    "HR":0,
    "RBI":25,
    "AVG":0.3,
    "WAR":1.7,
    "year":2000
  },
  {
    "Name":"Eric Owens",
    "Team":"SDP",
    "G":145,
    "PA":636,
    "HR":6,
    "RBI":51,
    "AVG":0.293,
    "WAR":1.7,
    "year":2000
  },
  {
    "Name":"Joe Girardi",
    "Team":"CHC",
    "G":106,
    "PA":407,
    "HR":6,
    "RBI":40,
    "AVG":0.278,
    "WAR":1.7,
    "year":2000
  },
  {
    "Name":"Henry Blanco",
    "Team":"MIL",
    "G":93,
    "PA":324,
    "HR":7,
    "RBI":31,
    "AVG":0.236,
    "WAR":1.7,
    "year":2000
  },
  {
    "Name":"Tom Goodwin",
    "Team":"- - -",
    "G":147,
    "PA":606,
    "HR":6,
    "RBI":58,
    "AVG":0.263,
    "WAR":1.7,
    "year":2000
  },
  {
    "Name":"Rey Sanchez",
    "Team":"KCR",
    "G":143,
    "PA":555,
    "HR":1,
    "RBI":38,
    "AVG":0.273,
    "WAR":1.7,
    "year":2000
  },
  {
    "Name":"Olmedo Saenz",
    "Team":"OAK",
    "G":76,
    "PA":247,
    "HR":9,
    "RBI":33,
    "AVG":0.313,
    "WAR":1.6,
    "year":2000
  },
  {
    "Name":"Brad Fullmer",
    "Team":"TOR",
    "G":133,
    "PA":524,
    "HR":32,
    "RBI":104,
    "AVG":0.295,
    "WAR":1.6,
    "year":2000
  },
  {
    "Name":"Jay Buhner",
    "Team":"SEA",
    "G":112,
    "PA":430,
    "HR":26,
    "RBI":82,
    "AVG":0.253,
    "WAR":1.6,
    "year":2000
  },
  {
    "Name":"Richie Sexson",
    "Team":"- - -",
    "G":148,
    "PA":607,
    "HR":30,
    "RBI":91,
    "AVG":0.272,
    "WAR":1.6,
    "year":2000
  },
  {
    "Name":"Paul Konerko",
    "Team":"CHW",
    "G":143,
    "PA":586,
    "HR":21,
    "RBI":97,
    "AVG":0.298,
    "WAR":1.6,
    "year":2000
  },
  {
    "Name":"Andres Galarraga",
    "Team":"ATL",
    "G":141,
    "PA":548,
    "HR":28,
    "RBI":100,
    "AVG":0.302,
    "WAR":1.5,
    "year":2000
  },
  {
    "Name":"Mark Quinn",
    "Team":"KCR",
    "G":135,
    "PA":544,
    "HR":20,
    "RBI":78,
    "AVG":0.294,
    "WAR":1.5,
    "year":2000
  },
  {
    "Name":"David McCarty",
    "Team":"KCR",
    "G":103,
    "PA":295,
    "HR":12,
    "RBI":53,
    "AVG":0.278,
    "WAR":1.5,
    "year":2000
  },
  {
    "Name":"Craig Biggio",
    "Team":"HOU",
    "G":101,
    "PA":466,
    "HR":8,
    "RBI":35,
    "AVG":0.268,
    "WAR":1.5,
    "year":2000
  },
  {
    "Name":"Eric Karros",
    "Team":"LAD",
    "G":155,
    "PA":663,
    "HR":31,
    "RBI":106,
    "AVG":0.25,
    "WAR":1.5,
    "year":2000
  },
  {
    "Name":"Bill Spiers",
    "Team":"HOU",
    "G":124,
    "PA":409,
    "HR":3,
    "RBI":43,
    "AVG":0.301,
    "WAR":1.5,
    "year":2000
  },
  {
    "Name":"Paul O'Neill",
    "Team":"NYY",
    "G":142,
    "PA":628,
    "HR":18,
    "RBI":100,
    "AVG":0.283,
    "WAR":1.5,
    "year":2000
  },
  {
    "Name":"Mark Loretta",
    "Team":"MIL",
    "G":91,
    "PA":399,
    "HR":7,
    "RBI":40,
    "AVG":0.281,
    "WAR":1.5,
    "year":2000
  },
  {
    "Name":"Jason Varitek",
    "Team":"BOS",
    "G":139,
    "PA":519,
    "HR":10,
    "RBI":65,
    "AVG":0.248,
    "WAR":1.5,
    "year":2000
  },
  {
    "Name":"Ray Lankford",
    "Team":"STL",
    "G":128,
    "PA":472,
    "HR":26,
    "RBI":65,
    "AVG":0.253,
    "WAR":1.4,
    "year":2000
  },
  {
    "Name":"Dante Bichette",
    "Team":"- - -",
    "G":155,
    "PA":636,
    "HR":23,
    "RBI":90,
    "AVG":0.294,
    "WAR":1.4,
    "year":2000
  },
  {
    "Name":"Geoff Blum",
    "Team":"MON",
    "G":124,
    "PA":379,
    "HR":11,
    "RBI":45,
    "AVG":0.283,
    "WAR":1.4,
    "year":2000
  },
  {
    "Name":"Derek Bell",
    "Team":"NYM",
    "G":144,
    "PA":622,
    "HR":18,
    "RBI":69,
    "AVG":0.266,
    "WAR":1.4,
    "year":2000
  },
  {
    "Name":"Troy O'Leary",
    "Team":"BOS",
    "G":138,
    "PA":563,
    "HR":13,
    "RBI":70,
    "AVG":0.261,
    "WAR":1.4,
    "year":2000
  },
  {
    "Name":"Mark Grudzielanek",
    "Team":"LAD",
    "G":148,
    "PA":676,
    "HR":7,
    "RBI":49,
    "AVG":0.279,
    "WAR":1.4,
    "year":2000
  },
  {
    "Name":"Felix Martinez",
    "Team":"TBD",
    "G":106,
    "PA":353,
    "HR":2,
    "RBI":17,
    "AVG":0.214,
    "WAR":1.4,
    "year":2000
  },
  {
    "Name":"J.T. Snow",
    "Team":"SFG",
    "G":155,
    "PA":627,
    "HR":19,
    "RBI":96,
    "AVG":0.284,
    "WAR":1.3,
    "year":2000
  },
  {
    "Name":"Eric Davis",
    "Team":"STL",
    "G":92,
    "PA":293,
    "HR":6,
    "RBI":40,
    "AVG":0.303,
    "WAR":1.3,
    "year":2000
  },
  {
    "Name":"Jay Bell",
    "Team":"ARI",
    "G":149,
    "PA":649,
    "HR":18,
    "RBI":68,
    "AVG":0.267,
    "WAR":1.3,
    "year":2000
  },
  {
    "Name":"Jacque Jones",
    "Team":"MIN",
    "G":154,
    "PA":552,
    "HR":19,
    "RBI":76,
    "AVG":0.285,
    "WAR":1.3,
    "year":2000
  },
  {
    "Name":"Ricky Gutierrez",
    "Team":"CHC",
    "G":125,
    "PA":542,
    "HR":11,
    "RBI":56,
    "AVG":0.276,
    "WAR":1.3,
    "year":2000
  },
  {
    "Name":"Cal Ripken",
    "Team":"BAL",
    "G":83,
    "PA":339,
    "HR":15,
    "RBI":56,
    "AVG":0.256,
    "WAR":1.3,
    "year":2000
  },
  {
    "Name":"Mike Darr",
    "Team":"SDP",
    "G":58,
    "PA":228,
    "HR":1,
    "RBI":30,
    "AVG":0.268,
    "WAR":1.3,
    "year":2000
  },
  {
    "Name":"Bill Mueller",
    "Team":"SFG",
    "G":153,
    "PA":631,
    "HR":10,
    "RBI":55,
    "AVG":0.268,
    "WAR":1.3,
    "year":2000
  },
  {
    "Name":"Doug Mirabelli",
    "Team":"SFG",
    "G":82,
    "PA":273,
    "HR":6,
    "RBI":28,
    "AVG":0.23,
    "WAR":1.3,
    "year":2000
  },
  {
    "Name":"Armando Rios",
    "Team":"SFG",
    "G":115,
    "PA":269,
    "HR":10,
    "RBI":50,
    "AVG":0.266,
    "WAR":1.2,
    "year":2000
  },
  {
    "Name":"Adrian Brown",
    "Team":"PIT",
    "G":104,
    "PA":340,
    "HR":4,
    "RBI":28,
    "AVG":0.315,
    "WAR":1.2,
    "year":2000
  },
  {
    "Name":"Mark McLemore",
    "Team":"SEA",
    "G":138,
    "PA":578,
    "HR":3,
    "RBI":46,
    "AVG":0.245,
    "WAR":1.2,
    "year":2000
  },
  {
    "Name":"Ramon Martinez",
    "Team":"SFG",
    "G":88,
    "PA":210,
    "HR":6,
    "RBI":25,
    "AVG":0.302,
    "WAR":1.1,
    "year":2000
  },
  {
    "Name":"Juan Encarnacion",
    "Team":"DET",
    "G":141,
    "PA":590,
    "HR":14,
    "RBI":72,
    "AVG":0.289,
    "WAR":1.1,
    "year":2000
  },
  {
    "Name":"Rusty Greer",
    "Team":"TEX",
    "G":105,
    "PA":453,
    "HR":8,
    "RBI":65,
    "AVG":0.297,
    "WAR":1.0,
    "year":2000
  },
  {
    "Name":"Lee Stevens",
    "Team":"MON",
    "G":123,
    "PA":501,
    "HR":22,
    "RBI":75,
    "AVG":0.265,
    "WAR":1.0,
    "year":2000
  },
  {
    "Name":"Joe Oliver",
    "Team":"SEA",
    "G":69,
    "PA":219,
    "HR":10,
    "RBI":35,
    "AVG":0.265,
    "WAR":1.0,
    "year":2000
  },
  {
    "Name":"Jeff Frye",
    "Team":"- - -",
    "G":106,
    "PA":371,
    "HR":1,
    "RBI":16,
    "AVG":0.307,
    "WAR":1.0,
    "year":2000
  },
  {
    "Name":"Jerry Hairston",
    "Team":"BAL",
    "G":49,
    "PA":212,
    "HR":5,
    "RBI":19,
    "AVG":0.256,
    "WAR":1.0,
    "year":2000
  },
  {
    "Name":"Mike Benjamin",
    "Team":"PIT",
    "G":93,
    "PA":255,
    "HR":2,
    "RBI":19,
    "AVG":0.27,
    "WAR":1.0,
    "year":2000
  },
  {
    "Name":"Glenallen Hill",
    "Team":"- - -",
    "G":104,
    "PA":321,
    "HR":27,
    "RBI":58,
    "AVG":0.293,
    "WAR":0.9,
    "year":2000
  },
  {
    "Name":"Tony Clark",
    "Team":"DET",
    "G":60,
    "PA":232,
    "HR":13,
    "RBI":37,
    "AVG":0.274,
    "WAR":0.9,
    "year":2000
  },
  {
    "Name":"Steve Cox",
    "Team":"TBD",
    "G":116,
    "PA":369,
    "HR":11,
    "RBI":35,
    "AVG":0.283,
    "WAR":0.9,
    "year":2000
  },
  {
    "Name":"Jose Canseco",
    "Team":"- - -",
    "G":98,
    "PA":401,
    "HR":15,
    "RBI":49,
    "AVG":0.252,
    "WAR":0.9,
    "year":2000
  },
  {
    "Name":"Tony Eusebio",
    "Team":"HOU",
    "G":74,
    "PA":249,
    "HR":7,
    "RBI":33,
    "AVG":0.28,
    "WAR":0.9,
    "year":2000
  },
  {
    "Name":"Albert Belle",
    "Team":"BAL",
    "G":141,
    "PA":622,
    "HR":23,
    "RBI":103,
    "AVG":0.281,
    "WAR":0.9,
    "year":2000
  },
  {
    "Name":"Bill Haselman",
    "Team":"TEX",
    "G":62,
    "PA":210,
    "HR":6,
    "RBI":26,
    "AVG":0.275,
    "WAR":0.9,
    "year":2000
  },
  {
    "Name":"Einar Diaz",
    "Team":"CLE",
    "G":75,
    "PA":275,
    "HR":4,
    "RBI":25,
    "AVG":0.272,
    "WAR":0.9,
    "year":2000
  },
  {
    "Name":"Ramon Hernandez",
    "Team":"OAK",
    "G":143,
    "PA":479,
    "HR":14,
    "RBI":62,
    "AVG":0.241,
    "WAR":0.9,
    "year":2000
  },
  {
    "Name":"Walt Weiss",
    "Team":"ATL",
    "G":80,
    "PA":227,
    "HR":0,
    "RBI":18,
    "AVG":0.26,
    "WAR":0.9,
    "year":2000
  },
  {
    "Name":"Russell Branyan",
    "Team":"CLE",
    "G":67,
    "PA":220,
    "HR":16,
    "RBI":38,
    "AVG":0.238,
    "WAR":0.8,
    "year":2000
  },
  {
    "Name":"Gabe Kapler",
    "Team":"TEX",
    "G":116,
    "PA":491,
    "HR":14,
    "RBI":66,
    "AVG":0.302,
    "WAR":0.8,
    "year":2000
  },
  {
    "Name":"Ruben Mateo",
    "Team":"TEX",
    "G":52,
    "PA":222,
    "HR":7,
    "RBI":19,
    "AVG":0.291,
    "WAR":0.8,
    "year":2000
  },
  {
    "Name":"Melvin Mora",
    "Team":"- - -",
    "G":132,
    "PA":464,
    "HR":8,
    "RBI":47,
    "AVG":0.275,
    "WAR":0.8,
    "year":2000
  },
  {
    "Name":"Luis Sojo",
    "Team":"- - -",
    "G":95,
    "PA":323,
    "HR":7,
    "RBI":37,
    "AVG":0.286,
    "WAR":0.8,
    "year":2000
  },
  {
    "Name":"Dave Martinez",
    "Team":"- - -",
    "G":132,
    "PA":513,
    "HR":5,
    "RBI":47,
    "AVG":0.274,
    "WAR":0.8,
    "year":2000
  },
  {
    "Name":"Ruben Rivera",
    "Team":"SDP",
    "G":135,
    "PA":479,
    "HR":17,
    "RBI":57,
    "AVG":0.208,
    "WAR":0.8,
    "year":2000
  },
  {
    "Name":"Jeff Reed",
    "Team":"CHC",
    "G":90,
    "PA":277,
    "HR":4,
    "RBI":25,
    "AVG":0.214,
    "WAR":0.8,
    "year":2000
  },
  {
    "Name":"David Ortiz",
    "Team":"MIN",
    "G":130,
    "PA":478,
    "HR":10,
    "RBI":63,
    "AVG":0.282,
    "WAR":0.7,
    "year":2000
  },
  {
    "Name":"Danny Bautista",
    "Team":"- - -",
    "G":131,
    "PA":388,
    "HR":11,
    "RBI":59,
    "AVG":0.285,
    "WAR":0.7,
    "year":2000
  },
  {
    "Name":"Gregg Zaun",
    "Team":"KCR",
    "G":83,
    "PA":282,
    "HR":7,
    "RBI":33,
    "AVG":0.274,
    "WAR":0.7,
    "year":2000
  },
  {
    "Name":"Craig Grebeck",
    "Team":"TOR",
    "G":66,
    "PA":270,
    "HR":3,
    "RBI":23,
    "AVG":0.295,
    "WAR":0.7,
    "year":2000
  },
  {
    "Name":"Wiki Gonzalez",
    "Team":"SDP",
    "G":95,
    "PA":319,
    "HR":5,
    "RBI":30,
    "AVG":0.232,
    "WAR":0.7,
    "year":2000
  },
  {
    "Name":"Shane Spencer",
    "Team":"NYY",
    "G":73,
    "PA":276,
    "HR":9,
    "RBI":40,
    "AVG":0.282,
    "WAR":0.6,
    "year":2000
  },
  {
    "Name":"Roger Cedeno",
    "Team":"HOU",
    "G":74,
    "PA":305,
    "HR":6,
    "RBI":26,
    "AVG":0.282,
    "WAR":0.6,
    "year":2000
  },
  {
    "Name":"Luis Alicea",
    "Team":"TEX",
    "G":139,
    "PA":619,
    "HR":6,
    "RBI":63,
    "AVG":0.294,
    "WAR":0.6,
    "year":2000
  },
  {
    "Name":"Brian Daubach",
    "Team":"BOS",
    "G":142,
    "PA":549,
    "HR":21,
    "RBI":76,
    "AVG":0.248,
    "WAR":0.6,
    "year":2000
  },
  {
    "Name":"Matt Williams",
    "Team":"ARI",
    "G":96,
    "PA":397,
    "HR":12,
    "RBI":47,
    "AVG":0.275,
    "WAR":0.6,
    "year":2000
  },
  {
    "Name":"Travis Lee",
    "Team":"- - -",
    "G":128,
    "PA":473,
    "HR":9,
    "RBI":54,
    "AVG":0.235,
    "WAR":0.6,
    "year":2000
  },
  {
    "Name":"Benji Gil",
    "Team":"ANA",
    "G":110,
    "PA":343,
    "HR":6,
    "RBI":23,
    "AVG":0.239,
    "WAR":0.6,
    "year":2000
  },
  {
    "Name":"Carlos Febles",
    "Team":"KCR",
    "G":100,
    "PA":399,
    "HR":2,
    "RBI":29,
    "AVG":0.257,
    "WAR":0.6,
    "year":2000
  },
  {
    "Name":"Kevin Stocker",
    "Team":"- - -",
    "G":110,
    "PA":409,
    "HR":2,
    "RBI":24,
    "AVG":0.219,
    "WAR":0.6,
    "year":2000
  },
  {
    "Name":"Mark Johnson",
    "Team":"CHW",
    "G":75,
    "PA":251,
    "HR":3,
    "RBI":23,
    "AVG":0.225,
    "WAR":0.6,
    "year":2000
  },
  {
    "Name":"Frank Catalanotto",
    "Team":"TEX",
    "G":103,
    "PA":326,
    "HR":10,
    "RBI":42,
    "AVG":0.291,
    "WAR":0.5,
    "year":2000
  },
  {
    "Name":"Pat Burrell",
    "Team":"PHI",
    "G":111,
    "PA":474,
    "HR":18,
    "RBI":79,
    "AVG":0.26,
    "WAR":0.5,
    "year":2000
  },
  {
    "Name":"Dean Palmer",
    "Team":"DET",
    "G":145,
    "PA":604,
    "HR":29,
    "RBI":102,
    "AVG":0.256,
    "WAR":0.5,
    "year":2000
  },
  {
    "Name":"Brent Mayne",
    "Team":"COL",
    "G":117,
    "PA":395,
    "HR":6,
    "RBI":64,
    "AVG":0.301,
    "WAR":0.5,
    "year":2000
  },
  {
    "Name":"Denny Hocking",
    "Team":"MIN",
    "G":134,
    "PA":433,
    "HR":4,
    "RBI":47,
    "AVG":0.298,
    "WAR":0.5,
    "year":2000
  },
  {
    "Name":"Tyler Houston",
    "Team":"MIL",
    "G":101,
    "PA":305,
    "HR":18,
    "RBI":43,
    "AVG":0.25,
    "WAR":0.5,
    "year":2000
  },
  {
    "Name":"Shawon Dunston",
    "Team":"STL",
    "G":98,
    "PA":231,
    "HR":12,
    "RBI":43,
    "AVG":0.25,
    "WAR":0.5,
    "year":2000
  },
  {
    "Name":"Raul Casanova",
    "Team":"MIL",
    "G":86,
    "PA":265,
    "HR":6,
    "RBI":36,
    "AVG":0.247,
    "WAR":0.5,
    "year":2000
  },
  {
    "Name":"Charlie Hayes",
    "Team":"MIL",
    "G":121,
    "PA":435,
    "HR":9,
    "RBI":46,
    "AVG":0.251,
    "WAR":0.5,
    "year":2000
  },
  {
    "Name":"Adam Kennedy",
    "Team":"ANA",
    "G":156,
    "PA":641,
    "HR":9,
    "RBI":72,
    "AVG":0.266,
    "WAR":0.5,
    "year":2000
  },
  {
    "Name":"Rickey Henderson",
    "Team":"- - -",
    "G":123,
    "PA":519,
    "HR":4,
    "RBI":32,
    "AVG":0.233,
    "WAR":0.5,
    "year":2000
  },
  {
    "Name":"Willie Greene",
    "Team":"CHC",
    "G":105,
    "PA":339,
    "HR":10,
    "RBI":37,
    "AVG":0.201,
    "WAR":0.5,
    "year":2000
  },
  {
    "Name":"Russ Johnson",
    "Team":"- - -",
    "G":100,
    "PA":263,
    "HR":2,
    "RBI":20,
    "AVG":0.239,
    "WAR":0.5,
    "year":2000
  },
  {
    "Name":"Chris Richard",
    "Team":"- - -",
    "G":62,
    "PA":239,
    "HR":14,
    "RBI":37,
    "AVG":0.265,
    "WAR":0.4,
    "year":2000
  },
  {
    "Name":"Hal Morris",
    "Team":"- - -",
    "G":99,
    "PA":204,
    "HR":3,
    "RBI":14,
    "AVG":0.278,
    "WAR":0.4,
    "year":2000
  },
  {
    "Name":"Jeff Conine",
    "Team":"BAL",
    "G":119,
    "PA":452,
    "HR":13,
    "RBI":46,
    "AVG":0.284,
    "WAR":0.4,
    "year":2000
  },
  {
    "Name":"Mike Stanley",
    "Team":"- - -",
    "G":90,
    "PA":331,
    "HR":14,
    "RBI":46,
    "AVG":0.238,
    "WAR":0.4,
    "year":2000
  },
  {
    "Name":"Jose Guillen",
    "Team":"TBD",
    "G":105,
    "PA":349,
    "HR":10,
    "RBI":41,
    "AVG":0.253,
    "WAR":0.4,
    "year":2000
  },
  {
    "Name":"Chris Widger",
    "Team":"- - -",
    "G":96,
    "PA":324,
    "HR":13,
    "RBI":35,
    "AVG":0.233,
    "WAR":0.4,
    "year":2000
  },
  {
    "Name":"Gerald Williams",
    "Team":"TBD",
    "G":146,
    "PA":682,
    "HR":21,
    "RBI":89,
    "AVG":0.274,
    "WAR":0.4,
    "year":2000
  },
  {
    "Name":"Luis Lopez",
    "Team":"MIL",
    "G":78,
    "PA":225,
    "HR":6,
    "RBI":27,
    "AVG":0.264,
    "WAR":0.4,
    "year":2000
  },
  {
    "Name":"Sandy Alomar Jr.",
    "Team":"CLE",
    "G":97,
    "PA":384,
    "HR":7,
    "RBI":42,
    "AVG":0.289,
    "WAR":0.4,
    "year":2000
  },
  {
    "Name":"Carlos Guillen",
    "Team":"SEA",
    "G":90,
    "PA":328,
    "HR":7,
    "RBI":42,
    "AVG":0.257,
    "WAR":0.4,
    "year":2000
  },
  {
    "Name":"Jose Offerman",
    "Team":"BOS",
    "G":116,
    "PA":527,
    "HR":9,
    "RBI":41,
    "AVG":0.255,
    "WAR":0.4,
    "year":2000
  },
  {
    "Name":"David Bell",
    "Team":"SEA",
    "G":133,
    "PA":512,
    "HR":11,
    "RBI":47,
    "AVG":0.247,
    "WAR":0.4,
    "year":2000
  },
  {
    "Name":"Chris Singleton",
    "Team":"CHW",
    "G":147,
    "PA":566,
    "HR":11,
    "RBI":62,
    "AVG":0.254,
    "WAR":0.4,
    "year":2000
  },
  {
    "Name":"Carlos Beltran",
    "Team":"KCR",
    "G":98,
    "PA":413,
    "HR":7,
    "RBI":44,
    "AVG":0.247,
    "WAR":0.4,
    "year":2000
  },
  {
    "Name":"Shane Halter",
    "Team":"DET",
    "G":105,
    "PA":265,
    "HR":3,
    "RBI":27,
    "AVG":0.261,
    "WAR":0.4,
    "year":2000
  },
  {
    "Name":"Luis Matos",
    "Team":"BAL",
    "G":72,
    "PA":201,
    "HR":1,
    "RBI":17,
    "AVG":0.225,
    "WAR":0.4,
    "year":2000
  },
  {
    "Name":"Erubiel Durazo",
    "Team":"ARI",
    "G":67,
    "PA":233,
    "HR":8,
    "RBI":33,
    "AVG":0.265,
    "WAR":0.3,
    "year":2000
  },
  {
    "Name":"Bubba Trammell",
    "Team":"- - -",
    "G":102,
    "PA":278,
    "HR":10,
    "RBI":45,
    "AVG":0.265,
    "WAR":0.3,
    "year":2000
  },
  {
    "Name":"Kevin Elster",
    "Team":"LAD",
    "G":80,
    "PA":259,
    "HR":14,
    "RBI":32,
    "AVG":0.227,
    "WAR":0.3,
    "year":2000
  },
  {
    "Name":"Chris Truby",
    "Team":"HOU",
    "G":78,
    "PA":279,
    "HR":11,
    "RBI":59,
    "AVG":0.26,
    "WAR":0.3,
    "year":2000
  },
  {
    "Name":"Rich Becker",
    "Team":"- - -",
    "G":115,
    "PA":357,
    "HR":8,
    "RBI":39,
    "AVG":0.242,
    "WAR":0.3,
    "year":2000
  },
  {
    "Name":"Chuck Knoblauch",
    "Team":"NYY",
    "G":102,
    "PA":457,
    "HR":5,
    "RBI":26,
    "AVG":0.283,
    "WAR":0.3,
    "year":2000
  },
  {
    "Name":"Bret Boone",
    "Team":"SDP",
    "G":127,
    "PA":525,
    "HR":19,
    "RBI":74,
    "AVG":0.251,
    "WAR":0.3,
    "year":2000
  },
  {
    "Name":"Neifi Perez",
    "Team":"COL",
    "G":162,
    "PA":699,
    "HR":10,
    "RBI":71,
    "AVG":0.287,
    "WAR":0.3,
    "year":2000
  },
  {
    "Name":"Damon Buford",
    "Team":"CHC",
    "G":150,
    "PA":556,
    "HR":15,
    "RBI":48,
    "AVG":0.251,
    "WAR":0.3,
    "year":2000
  },
  {
    "Name":"Brian Hunter",
    "Team":"- - -",
    "G":104,
    "PA":274,
    "HR":1,
    "RBI":14,
    "AVG":0.267,
    "WAR":0.3,
    "year":2000
  },
  {
    "Name":"Dan Wilson",
    "Team":"SEA",
    "G":90,
    "PA":303,
    "HR":5,
    "RBI":27,
    "AVG":0.235,
    "WAR":0.3,
    "year":2000
  },
  {
    "Name":"Mike Redmond",
    "Team":"FLA",
    "G":87,
    "PA":235,
    "HR":0,
    "RBI":15,
    "AVG":0.252,
    "WAR":0.3,
    "year":2000
  },
  {
    "Name":"Shane Andrews",
    "Team":"CHC",
    "G":66,
    "PA":222,
    "HR":14,
    "RBI":39,
    "AVG":0.229,
    "WAR":0.2,
    "year":2000
  },
  {
    "Name":"Scott Spiezio",
    "Team":"ANA",
    "G":123,
    "PA":345,
    "HR":17,
    "RBI":49,
    "AVG":0.242,
    "WAR":0.2,
    "year":2000
  },
  {
    "Name":"Wally Joyner",
    "Team":"ATL",
    "G":119,
    "PA":260,
    "HR":5,
    "RBI":32,
    "AVG":0.281,
    "WAR":0.2,
    "year":2000
  },
  {
    "Name":"Tino Martinez",
    "Team":"NYY",
    "G":155,
    "PA":632,
    "HR":16,
    "RBI":91,
    "AVG":0.258,
    "WAR":0.2,
    "year":2000
  },
  {
    "Name":"Reggie Sanders",
    "Team":"ATL",
    "G":103,
    "PA":377,
    "HR":11,
    "RBI":37,
    "AVG":0.232,
    "WAR":0.2,
    "year":2000
  },
  {
    "Name":"Keith Lockhart",
    "Team":"ATL",
    "G":113,
    "PA":313,
    "HR":2,
    "RBI":32,
    "AVG":0.265,
    "WAR":0.2,
    "year":2000
  },
  {
    "Name":"Dave Berg",
    "Team":"FLA",
    "G":82,
    "PA":245,
    "HR":1,
    "RBI":21,
    "AVG":0.252,
    "WAR":0.2,
    "year":2000
  },
  {
    "Name":"Doug Glanville",
    "Team":"PHI",
    "G":154,
    "PA":689,
    "HR":8,
    "RBI":52,
    "AVG":0.275,
    "WAR":0.2,
    "year":2000
  },
  {
    "Name":"Fred McGriff",
    "Team":"TBD",
    "G":158,
    "PA":664,
    "HR":27,
    "RBI":106,
    "AVG":0.277,
    "WAR":0.1,
    "year":2000
  },
  {
    "Name":"Andy Tracy",
    "Team":"MON",
    "G":83,
    "PA":218,
    "HR":11,
    "RBI":32,
    "AVG":0.26,
    "WAR":0.1,
    "year":2000
  },
  {
    "Name":"Scott Hatteberg",
    "Team":"BOS",
    "G":92,
    "PA":271,
    "HR":8,
    "RBI":36,
    "AVG":0.265,
    "WAR":0.1,
    "year":2000
  },
  {
    "Name":"Terry Shumpert",
    "Team":"COL",
    "G":115,
    "PA":300,
    "HR":9,
    "RBI":40,
    "AVG":0.259,
    "WAR":0.1,
    "year":2000
  },
  {
    "Name":"Al Martin",
    "Team":"- - -",
    "G":135,
    "PA":523,
    "HR":15,
    "RBI":36,
    "AVG":0.285,
    "WAR":0.1,
    "year":2000
  },
  {
    "Name":"Stan Javier",
    "Team":"SEA",
    "G":105,
    "PA":392,
    "HR":5,
    "RBI":40,
    "AVG":0.275,
    "WAR":0.1,
    "year":2000
  },
  {
    "Name":"Midre Cummings",
    "Team":"- - -",
    "G":98,
    "PA":227,
    "HR":4,
    "RBI":24,
    "AVG":0.277,
    "WAR":0.1,
    "year":2000
  },
  {
    "Name":"Calvin Murray",
    "Team":"SFG",
    "G":108,
    "PA":229,
    "HR":2,
    "RBI":22,
    "AVG":0.242,
    "WAR":0.1,
    "year":2000
  },
  {
    "Name":"Mike DiFelice",
    "Team":"TBD",
    "G":60,
    "PA":223,
    "HR":6,
    "RBI":19,
    "AVG":0.24,
    "WAR":0.1,
    "year":2000
  },
  {
    "Name":"Carlos Hernandez",
    "Team":"- - -",
    "G":75,
    "PA":270,
    "HR":3,
    "RBI":35,
    "AVG":0.256,
    "WAR":0.1,
    "year":2000
  },
  {
    "Name":"Scott Brosius",
    "Team":"NYY",
    "G":135,
    "PA":519,
    "HR":16,
    "RBI":64,
    "AVG":0.23,
    "WAR":0.1,
    "year":2000
  },
  {
    "Name":"John Flaherty",
    "Team":"TBD",
    "G":109,
    "PA":418,
    "HR":10,
    "RBI":39,
    "AVG":0.261,
    "WAR":0.1,
    "year":2000
  },
  {
    "Name":"Clay Bellinger",
    "Team":"NYY",
    "G":98,
    "PA":209,
    "HR":6,
    "RBI":21,
    "AVG":0.207,
    "WAR":0.1,
    "year":2000
  },
  {
    "Name":"Kelly Stinnett",
    "Team":"ARI",
    "G":76,
    "PA":265,
    "HR":8,
    "RBI":33,
    "AVG":0.217,
    "WAR":0.1,
    "year":2000
  },
  {
    "Name":"Todd Walker",
    "Team":"- - -",
    "G":80,
    "PA":283,
    "HR":9,
    "RBI":44,
    "AVG":0.29,
    "WAR":0.0,
    "year":2000
  },
  {
    "Name":"Henry Rodriguez",
    "Team":"- - -",
    "G":112,
    "PA":410,
    "HR":20,
    "RBI":61,
    "AVG":0.256,
    "WAR":0.0,
    "year":2000
  },
  {
    "Name":"Julio Lugo",
    "Team":"HOU",
    "G":116,
    "PA":465,
    "HR":10,
    "RBI":40,
    "AVG":0.283,
    "WAR":0.0,
    "year":2000
  },
  {
    "Name":"Benito Santiago",
    "Team":"CIN",
    "G":89,
    "PA":277,
    "HR":8,
    "RBI":45,
    "AVG":0.262,
    "WAR":0.0,
    "year":2000
  },
  {
    "Name":"Tony Womack",
    "Team":"ARI",
    "G":146,
    "PA":659,
    "HR":7,
    "RBI":57,
    "AVG":0.271,
    "WAR":0.0,
    "year":2000
  },
  {
    "Name":"Jose Hernandez",
    "Team":"MIL",
    "G":124,
    "PA":496,
    "HR":11,
    "RBI":59,
    "AVG":0.244,
    "WAR":0.0,
    "year":2000
  },
  {
    "Name":"Warren Morris",
    "Team":"PIT",
    "G":144,
    "PA":606,
    "HR":3,
    "RBI":43,
    "AVG":0.259,
    "WAR":0.0,
    "year":2000
  },
  {
    "Name":"Jeff Reboulet",
    "Team":"KCR",
    "G":66,
    "PA":212,
    "HR":0,
    "RBI":14,
    "AVG":0.242,
    "WAR":0.0,
    "year":2000
  },
  {
    "Name":"Chad Curtis",
    "Team":"TEX",
    "G":108,
    "PA":381,
    "HR":8,
    "RBI":48,
    "AVG":0.272,
    "WAR":-0.1,
    "year":2000
  },
  {
    "Name":"Enrique Wilson",
    "Team":"- - -",
    "G":80,
    "PA":263,
    "HR":5,
    "RBI":27,
    "AVG":0.293,
    "WAR":-0.1,
    "year":2000
  },
  {
    "Name":"Harold Baines",
    "Team":"- - -",
    "G":96,
    "PA":320,
    "HR":11,
    "RBI":39,
    "AVG":0.254,
    "WAR":-0.1,
    "year":2000
  },
  {
    "Name":"Luis Polonia",
    "Team":"- - -",
    "G":117,
    "PA":383,
    "HR":7,
    "RBI":30,
    "AVG":0.276,
    "WAR":-0.1,
    "year":2000
  },
  {
    "Name":"Ron Coomer",
    "Team":"MIN",
    "G":140,
    "PA":589,
    "HR":16,
    "RBI":82,
    "AVG":0.27,
    "WAR":-0.1,
    "year":2000
  },
  {
    "Name":"Torii Hunter",
    "Team":"MIN",
    "G":99,
    "PA":358,
    "HR":5,
    "RBI":44,
    "AVG":0.28,
    "WAR":-0.1,
    "year":2000
  },
  {
    "Name":"Cristian Guzman",
    "Team":"MIN",
    "G":156,
    "PA":690,
    "HR":8,
    "RBI":54,
    "AVG":0.247,
    "WAR":-0.1,
    "year":2000
  },
  {
    "Name":"Mark Smith",
    "Team":"FLA",
    "G":104,
    "PA":213,
    "HR":5,
    "RBI":27,
    "AVG":0.245,
    "WAR":-0.1,
    "year":2000
  },
  {
    "Name":"Alberto T. Castillo",
    "Team":"TOR",
    "G":66,
    "PA":211,
    "HR":1,
    "RBI":16,
    "AVG":0.211,
    "WAR":-0.1,
    "year":2000
  },
  {
    "Name":"Daryle Ward",
    "Team":"HOU",
    "G":119,
    "PA":281,
    "HR":20,
    "RBI":47,
    "AVG":0.258,
    "WAR":-0.2,
    "year":2000
  },
  {
    "Name":"Butch Huskey",
    "Team":"- - -",
    "G":109,
    "PA":356,
    "HR":9,
    "RBI":45,
    "AVG":0.261,
    "WAR":-0.2,
    "year":2000
  },
  {
    "Name":"Jeremy Giambi",
    "Team":"OAK",
    "G":104,
    "PA":302,
    "HR":10,
    "RBI":50,
    "AVG":0.254,
    "WAR":-0.2,
    "year":2000
  },
  {
    "Name":"Ed Sprague",
    "Team":"- - -",
    "G":106,
    "PA":298,
    "HR":12,
    "RBI":36,
    "AVG":0.243,
    "WAR":-0.2,
    "year":2000
  },
  {
    "Name":"Jeff Abbott",
    "Team":"CHW",
    "G":80,
    "PA":242,
    "HR":3,
    "RBI":29,
    "AVG":0.274,
    "WAR":-0.2,
    "year":2000
  },
  {
    "Name":"Jay Canizaro",
    "Team":"MIN",
    "G":102,
    "PA":371,
    "HR":7,
    "RBI":40,
    "AVG":0.269,
    "WAR":-0.2,
    "year":2000
  },
  {
    "Name":"Lenny Harris",
    "Team":"- - -",
    "G":112,
    "PA":248,
    "HR":4,
    "RBI":26,
    "AVG":0.26,
    "WAR":-0.2,
    "year":2000
  },
  {
    "Name":"John Mabry",
    "Team":"- - -",
    "G":96,
    "PA":244,
    "HR":8,
    "RBI":32,
    "AVG":0.235,
    "WAR":-0.2,
    "year":2000
  },
  {
    "Name":"Pat Meares",
    "Team":"PIT",
    "G":132,
    "PA":514,
    "HR":13,
    "RBI":47,
    "AVG":0.24,
    "WAR":-0.2,
    "year":2000
  },
  {
    "Name":"Paul Bako",
    "Team":"- - -",
    "G":81,
    "PA":251,
    "HR":2,
    "RBI":20,
    "AVG":0.226,
    "WAR":-0.2,
    "year":2000
  },
  {
    "Name":"Darren Lewis",
    "Team":"BOS",
    "G":97,
    "PA":303,
    "HR":2,
    "RBI":17,
    "AVG":0.241,
    "WAR":-0.2,
    "year":2000
  },
  {
    "Name":"Alex Gonzalez",
    "Team":"TOR",
    "G":141,
    "PA":591,
    "HR":15,
    "RBI":69,
    "AVG":0.252,
    "WAR":-0.3,
    "year":2000
  },
  {
    "Name":"Juan Pierre",
    "Team":"COL",
    "G":51,
    "PA":219,
    "HR":0,
    "RBI":20,
    "AVG":0.31,
    "WAR":-0.3,
    "year":2000
  },
  {
    "Name":"Alex Cora",
    "Team":"LAD",
    "G":109,
    "PA":394,
    "HR":4,
    "RBI":32,
    "AVG":0.238,
    "WAR":-0.3,
    "year":2000
  },
  {
    "Name":"Matt Stairs",
    "Team":"OAK",
    "G":143,
    "PA":562,
    "HR":21,
    "RBI":81,
    "AVG":0.227,
    "WAR":-0.4,
    "year":2000
  },
  {
    "Name":"Craig Paquette",
    "Team":"STL",
    "G":134,
    "PA":420,
    "HR":15,
    "RBI":61,
    "AVG":0.245,
    "WAR":-0.4,
    "year":2000
  },
  {
    "Name":"Greg Norton",
    "Team":"CHW",
    "G":71,
    "PA":231,
    "HR":6,
    "RBI":28,
    "AVG":0.244,
    "WAR":-0.4,
    "year":2000
  },
  {
    "Name":"Orlando Cabrera",
    "Team":"MON",
    "G":125,
    "PA":454,
    "HR":13,
    "RBI":55,
    "AVG":0.237,
    "WAR":-0.4,
    "year":2000
  },
  {
    "Name":"Juan Castro",
    "Team":"CIN",
    "G":82,
    "PA":244,
    "HR":4,
    "RBI":23,
    "AVG":0.241,
    "WAR":-0.4,
    "year":2000
  },
  {
    "Name":"Jose Vizcaino",
    "Team":"- - -",
    "G":113,
    "PA":297,
    "HR":0,
    "RBI":14,
    "AVG":0.251,
    "WAR":-0.4,
    "year":2000
  },
  {
    "Name":"Vinny Castilla",
    "Team":"TBD",
    "G":85,
    "PA":354,
    "HR":6,
    "RBI":42,
    "AVG":0.221,
    "WAR":-0.4,
    "year":2000
  },
  {
    "Name":"Jose Nieves",
    "Team":"CHC",
    "G":82,
    "PA":213,
    "HR":5,
    "RBI":24,
    "AVG":0.212,
    "WAR":-0.5,
    "year":2000
  },
  {
    "Name":"Eddie Taubensee",
    "Team":"CIN",
    "G":81,
    "PA":291,
    "HR":6,
    "RBI":24,
    "AVG":0.267,
    "WAR":-0.6,
    "year":2000
  },
  {
    "Name":"Ricky Ledee",
    "Team":"- - -",
    "G":137,
    "PA":531,
    "HR":13,
    "RBI":77,
    "AVG":0.236,
    "WAR":-0.6,
    "year":2000
  },
  {
    "Name":"Andy Fox",
    "Team":"- - -",
    "G":100,
    "PA":275,
    "HR":4,
    "RBI":20,
    "AVG":0.232,
    "WAR":-0.6,
    "year":2000
  },
  {
    "Name":"Miguel Cairo",
    "Team":"TBD",
    "G":119,
    "PA":417,
    "HR":1,
    "RBI":34,
    "AVG":0.261,
    "WAR":-0.7,
    "year":2000
  },
  {
    "Name":"Wilton Guerrero",
    "Team":"MON",
    "G":127,
    "PA":314,
    "HR":2,
    "RBI":23,
    "AVG":0.267,
    "WAR":-0.7,
    "year":2000
  },
  {
    "Name":"Mickey Morandini",
    "Team":"- - -",
    "G":126,
    "PA":457,
    "HR":0,
    "RBI":29,
    "AVG":0.257,
    "WAR":-0.7,
    "year":2000
  },
  {
    "Name":"Aramis Ramirez",
    "Team":"PIT",
    "G":73,
    "PA":274,
    "HR":6,
    "RBI":35,
    "AVG":0.256,
    "WAR":-0.8,
    "year":2000
  },
  {
    "Name":"Manny Alexander",
    "Team":"BOS",
    "G":101,
    "PA":209,
    "HR":4,
    "RBI":19,
    "AVG":0.211,
    "WAR":-0.8,
    "year":2000
  },
  {
    "Name":"Wil Cordero",
    "Team":"- - -",
    "G":127,
    "PA":536,
    "HR":16,
    "RBI":68,
    "AVG":0.276,
    "WAR":-0.9,
    "year":2000
  },
  {
    "Name":"Royce Clayton",
    "Team":"TEX",
    "G":148,
    "PA":573,
    "HR":14,
    "RBI":54,
    "AVG":0.242,
    "WAR":-0.9,
    "year":2000
  },
  {
    "Name":"Desi Relaford",
    "Team":"- - -",
    "G":128,
    "PA":502,
    "HR":5,
    "RBI":46,
    "AVG":0.215,
    "WAR":-0.9,
    "year":2000
  },
  {
    "Name":"Alex Ramirez",
    "Team":"- - -",
    "G":84,
    "PA":240,
    "HR":9,
    "RBI":30,
    "AVG":0.247,
    "WAR":-1.0,
    "year":2000
  },
  {
    "Name":"Tim Bogar",
    "Team":"HOU",
    "G":110,
    "PA":351,
    "HR":7,
    "RBI":33,
    "AVG":0.207,
    "WAR":-1.0,
    "year":2000
  },
  {
    "Name":"Bobby Bonilla",
    "Team":"ATL",
    "G":114,
    "PA":278,
    "HR":5,
    "RBI":28,
    "AVG":0.255,
    "WAR":-1.1,
    "year":2000
  },
  {
    "Name":"Kevin Young",
    "Team":"PIT",
    "G":132,
    "PA":541,
    "HR":20,
    "RBI":88,
    "AVG":0.258,
    "WAR":-1.2,
    "year":2000
  },
  {
    "Name":"Peter Bergeron",
    "Team":"MON",
    "G":148,
    "PA":592,
    "HR":5,
    "RBI":31,
    "AVG":0.245,
    "WAR":-1.5,
    "year":2000
  },
  {
    "Name":"Marty Cordova",
    "Team":"TOR",
    "G":62,
    "PA":221,
    "HR":4,
    "RBI":18,
    "AVG":0.245,
    "WAR":-1.5,
    "year":2000
  },
  {
    "Name":"Kevin Jordan",
    "Team":"PHI",
    "G":109,
    "PA":358,
    "HR":5,
    "RBI":36,
    "AVG":0.22,
    "WAR":-1.5,
    "year":2000
  },
  {
    "Name":"Mike Lamb",
    "Team":"TEX",
    "G":138,
    "PA":538,
    "HR":6,
    "RBI":47,
    "AVG":0.278,
    "WAR":-1.6,
    "year":2000
  },
  {
    "Name":"Homer Bush",
    "Team":"TOR",
    "G":76,
    "PA":325,
    "HR":1,
    "RBI":18,
    "AVG":0.215,
    "WAR":-1.6,
    "year":2000
  },
  {
    "Name":"Mike Lansing",
    "Team":"- - -",
    "G":139,
    "PA":548,
    "HR":11,
    "RBI":60,
    "AVG":0.24,
    "WAR":-1.7,
    "year":2000
  },
  {
    "Name":"Marquis Grissom",
    "Team":"MIL",
    "G":146,
    "PA":640,
    "HR":14,
    "RBI":62,
    "AVG":0.244,
    "WAR":-1.8,
    "year":2000
  },
  {
    "Name":"Michael Barrett",
    "Team":"MON",
    "G":89,
    "PA":297,
    "HR":1,
    "RBI":22,
    "AVG":0.214,
    "WAR":-1.8,
    "year":2000
  },
  {
    "Name":"Alex Gonzalez",
    "Team":"FLA",
    "G":109,
    "PA":407,
    "HR":7,
    "RBI":42,
    "AVG":0.2,
    "WAR":-2.0,
    "year":2000
  }
]